{
  "title": "Friday Facts #269 - Roadmap update &amp; Transport belt perspective",
  "counts": {
    "the": 105,
    "to": 42,
    "of": 37,
    "and": 35,
    "we": 30,
    "a": 26,
    "it": 24,
    "in": 21,
    "is": 20,
    "belt": 18,
    "be": 16,
    "more": 13,
    "you": 13,
    "belts": 12,
    "this": 11,
    "which": 11,
    "fff": 11,
    "can": 10,
    "but": 10,
    "all": 10,
    "that": 10,
    "with": 10,
    "for": 9,
    "are": 9,
    "have": 8,
    "when": 8,
    "they": 8,
    "will": 8,
    "how": 8,
    "now": 8,
    "see": 8,
    "our": 7,
    "some": 7,
    "time": 7,
    "on": 7,
    "tile": 7,
    "structure": 7,
    "underground": 7,
    "new": 6,
    "was": 6,
    "things": 6,
    "much": 6,
    "lot": 5,
    "game": 5,
    "final": 5,
    "before": 5,
    "not": 5,
    "gui": 5,
    "over": 5,
    "just": 5,
    "would": 5,
    "sprites": 5,
    "sprite": 5,
    "endings": 5,
    "pieces": 5,
    "plan": 4,
    "everything": 4,
    "done": 4,
    "little": 4,
    "each": 4,
    "know": 4,
    "mainly": 4,
    "than": 4,
    "from": 4,
    "by": 4,
    "into": 4,
    "so": 4,
    "its": 4,
    "because": 4,
    "should": 4,
    "has": 4,
    "problems": 4,
    "as": 4,
    "release": 3,
    "going": 3,
    "finished": 3,
    "finish": 3,
    "at": 3,
    "too": 3,
    "what": 3,
    "tried": 3,
    "few": 3,
    "need": 3,
    "idea": 3,
    "following": 3,
    "most": 3,
    "high": 3,
    "graphics": 3,
    "transport": 3,
    "perspective": 3,
    "many": 3,
    "sometimes": 3,
    "them": 3,
    "changing": 3,
    "their": 3,
    "makes": 3,
    "or": 3,
    "already": 3,
    "space": 3,
    "show": 3,
    "shape": 3,
    "work": 3,
    "flipping": 3,
    "structures": 3,
    "front": 3,
    "been": 2,
    "version": 2,
    "factorio": 2,
    "worked": 2,
    "way": 2,
    "then": 2,
    "started": 2,
    "taking": 2,
    "long": 2,
    "even": 2,
    "issue": 2,
    "become": 2,
    "past": 2,
    "through": 2,
    "decided": 2,
    "do": 2,
    "make": 2,
    "kind": 2,
    "task": 2,
    "get": 2,
    "working": 2,
    "result": 2,
    "if": 2,
    "goes": 2,
    "months": 2,
    "after": 2,
    "contain": 2,
    "also": 2,
    "main": 2,
    "exactly": 2,
    "resolution": 2,
    "design": 2,
    "tiles": 2,
    "being": 2,
    "whole": 2,
    "found": 2,
    "ground": 2,
    "fit": 2,
    "items": 2,
    "big": 2,
    "portion": 2,
    "there": 2,
    "very": 2,
    "impossible": 2,
    "where": 2,
    "go": 2,
    "edge": 2,
    "sorting": 2,
    "bottom": 2,
    "horizontal": 2,
    "curves": 2,
    "right": 2,
    "demonstrate": 2,
    "underneath": 2,
    "albert": 2,
    "one": 2,
    "possible": 2,
    "an": 2,
    "ending": 2,
    "only": 2,
    "cant": 2,
    "means": 2,
    "glitches": 2,
    "shadows": 2,
    "picture": 2,
    "correct": 2,
    "use": 2,
    "fix": 2,
    "breaking": 2,
    "other": 2,
    "logic": 2,
    "save": 2,
    "vram": 2,
    "i": 2,
    "us": 2,
    "mods": 2,
    "were": 2,
    "multiple": 2,
    "cases": 2,
    "always": 2,
    "patch": 2,
    "prevents": 2,
    "overlapping": 2,
    "roadmap": 1,
    "update": 1,
    "kovarex": 1,
    "people": 1,
    "asking": 1,
    "recently": 1,
    "expect": 1,
    "original": 1,
    "ideally": 1,
    "end": 1,
    "beginning": 1,
    "year": 1,
    "usual": 1,
    "quite": 1,
    "bit": 1,
    "werent": 1,
    "sure": 1,
    "realistic": 1,
    "timeframe": 1,
    "help": 1,
    "organized": 1,
    "weeks": 1,
    "went": 1,
    "list": 1,
    "development": 1,
    "tasks": 1,
    "finalize": 1,
    "removed": 1,
    "cut": 1,
    "added": 1,
    "missing": 1,
    "estimate": 1,
    "general": 1,
    "conscious": 1,
    "who": 1,
    "accurate": 1,
    "estimates": 1,
    "well": 1,
    "could": 1,
    "probably": 1,
    "something": 1,
    "wanted": 1,
    "hear": 1,
    "rounds": 1,
    "discussions": 1,
    "split": 1,
    "releases": 1,
    "up": 1,
    "point": 1,
    "render": 1,
    "backend": 1,
    "helps": 1,
    "performance": 1,
    "solves": 1,
    "issues": 1,
    "graphical": 1,
    "updates": 1,
    "walls": 1,
    "gates": 1,
    "turrets": 1,
    "biters": 1,
    "spawners": 1,
    "electric": 1,
    "poles": 1,
    "reskin": 1,
    "map": 1,
    "editor": 1,
    "resource": 1,
    "generation": 1,
    "overhaul": 1,
    "robot": 1,
    "construction": 1,
    "tools": 1,
    "rich": 1,
    "text": 1,
    "include": 1,
    "soon": 1,
    "enough": 1,
    "redoing": 1,
    "important": 1,
    "guis": 1,
    "action": 1,
    "bar": 1,
    "character": 1,
    "screen": 1,
    "train": 1,
    "play": 1,
    "tooltips": 1,
    "fluid": 1,
    "optimisations": 1,
    "several": 1,
    "smaller": 1,
    "depends": 1,
    "during": 1,
    "january": 1,
    "announce": 1,
    "precisely": 1,
    "advance": 1,
    "once": 1,
    "stable": 1,
    "tutorial": 1,
    "campaign": 1,
    "mini": 1,
    "tutorials": 1,
    "revision": 1,
    "rest": 1,
    "remaining": 1,
    "res": 1,
    "polish": 1,
    "obviously": 1,
    "dont": 1,
    "ready": 1,
    "hope": 1,
    "sooner": 1,
    "v": 1,
    "reworked": 1,
    "bringing": 1,
    "camera": 1,
    "angle": 1,
    "degrees": 1,
    "real": 1,
    "projection": 1,
    "rectangular": 1,
    "contradicted": 1,
    "square": 1,
    "contradiction": 1,
    "challenges": 1,
    "addressing": 1,
    "might": 1,
    "remember": 1,
    "old": 1,
    "rails": 1,
    "concrete": 1,
    "grid": 1,
    "trains": 1,
    "did": 1,
    "stretch": 1,
    "solution": 1,
    "last": 1,
    "perspectively": 1,
    "incorrect": 1,
    "entity": 1,
    "basic": 1,
    "give": 1,
    "wallstructure": 1,
    "bring": 1,
    "off": 1,
    "create": 1,
    "illusion": 1,
    "world": 1,
    "correctly": 1,
    "two": 1,
    "limitations": 1,
    "lanes": 1,
    "changed": 1,
    "occupy": 1,
    "anything": 1,
    "extra": 1,
    "shame": 1,
    "abandon": 1,
    "conclusion": 1,
    "physically": 1,
    "thought": 1,
    "works": 1,
    "safe": 1,
    "gives": 1,
    "desired": 1,
    "effect": 1,
    "verticals": 1,
    "happy": 1,
    "pixels": 1,
    "side": 1,
    "add": 1,
    "shadow": 1,
    "height": 1,
    "smallest": 1,
    "unit": 1,
    "build": 1,
    "concept": 1,
    "reverse": 1,
    "reversed": 1,
    "running": 1,
    "spent": 1,
    "hours": 1,
    "trying": 1,
    "find": 1,
    "holes": 1,
    "movement": 1,
    "versus": 1,
    "massive": 1,
    "holding": 1,
    "limited": 1,
    "every": 1,
    "pixel": 1,
    "matters": 1,
    "arrived": 1,
    "iterations": 1,
    "experiments": 1,
    "tests": 1,
    "previously": 1,
    "didnt": 1,
    "matter": 1,
    "disappeared": 1,
    "since": 1,
    "full": 1,
    "loop": 1,
    "constraining": 1,
    "artist": 1,
    "exact": 1,
    "integer": 1,
    "amount": 1,
    "order": 1,
    "animation": 1,
    "normal": 1,
    "piecesfor": 1,
    "piece": 1,
    "bend": 1,
    "feasible": 1,
    "option": 1,
    "still": 1,
    "longer": 1,
    "invites": 1,
    "bunch": 1,
    "had": 1,
    "easy": 1,
    "solutions": 1,
    "handled": 1,
    "seems": 1,
    "less": 1,
    "until": 1,
    "realize": 1,
    "flipped": 1,
    "engine": 1,
    "causes": 1,
    "break": 1,
    "entirely": 1,
    "while": 1,
    "curve": 1,
    "lighting": 1,
    "isnt": 1,
    "having": 1,
    "great": 1,
    "either": 1,
    "wrong": 1,
    "same": 1,
    "without": 1,
    "therefore": 1,
    "finally": 1,
    "getting": 1,
    "rid": 1,
    "originally": 1,
    "used": 1,
    "significant": 1,
    "nowadays": 1,
    "sense": 1,
    "memory": 1,
    "costs": 1,
    "visible": 1,
    "entities": 1,
    "super": 1,
    "weird": 1,
    "fact": 1,
    "defined": 1,
    "almost": 1,
    "circle": 1,
    "fourth": 1,
    "mirrored": 1,
    "reasons": 1,
    "rotation": 1,
    "own": 1,
    "unique": 1,
    "allows": 1,
    "creative": 1,
    "custom": 1,
    "easier": 1,
    "caused": 1,
    "exceeding": 1,
    "edges": 1,
    "drawing": 1,
    "incorrectly": 1,
    "showing": 1,
    "shouldnt": 1,
    "badly": 1,
    "speaking": 1,
    "about": 1,
    "redesigning": 1,
    "times": 1,
    "ideal": 1,
    "opportunity": 1,
    "redesign": 1,
    "alone": 1,
    "couldnt": 1,
    "drawn": 1,
    "above": 1,
    "icons": 1,
    "below": 1,
    "border": 1,
    "draw": 1,
    "happen": 1,
    "neither": 1,
    "previous": 1,
    "present": 1,
    "screenshot": 1,
    "define": 1,
    "backpatch": 1,
    "frontpatch": 1,
    "layers": 1,
    "back": 1,
    "inside": 1,
    "fits": 1,
    "better": 1,
    "rounded": 1,
    "covers": 1,
    "needs": 1,
    "cover": 1,
    "reveals": 1,
    "bonus": 1,
    "variant": 1,
    "shows": 1,
    "hole": 1,
    "sideload": 1,
    "iterating": 1,
    "fixing": 1,
    "solving": 1,
    "feel": 1,
    "natural": 1,
    "believe": 1,
    "positive": 1,
    "impact": 1,
    "your": 1,
    "experience": 1,
    "let": 1,
    "think": 1,
    "forum": 1
  }
}