{
  "title": "Friday Facts #2",
  "counts": {
    "the": 53,
    "to": 21,
    "a": 19,
    "and": 17,
    "we": 16,
    "of": 14,
    "it": 13,
    "has": 12,
    "that": 12,
    "is": 10,
    "for": 10,
    "been": 9,
    "on": 8,
    "in": 7,
    "are": 7,
    "will": 7,
    "after": 6,
    "but": 6,
    "wiki": 6,
    "you": 6,
    "when": 5,
    "by": 5,
    "there": 5,
    "was": 5,
    "some": 5,
    "game": 5,
    "with": 5,
    "this": 5,
    "as": 5,
    "so": 5,
    "all": 5,
    "he": 5,
    "from": 4,
    "now": 4,
    "people": 4,
    "they": 4,
    "were": 4,
    "be": 4,
    "have": 4,
    "us": 4,
    "while": 4,
    "indie": 4,
    "another": 3,
    "factorio": 3,
    "here": 3,
    "forum": 3,
    "biters": 3,
    "an": 3,
    "would": 3,
    "enemy": 3,
    "up": 3,
    "player": 3,
    "or": 3,
    "which": 3,
    "at": 3,
    "started": 3,
    "also": 3,
    "new": 3,
    "because": 3,
    "small": 3,
    "week": 3,
    "what": 3,
    "well": 3,
    "animation": 3,
    "can": 3,
    "happened": 3,
    "workshop": 3,
    "about": 3,
    "post": 3,
    "release": 2,
    "last": 2,
    "friday": 2,
    "lot": 2,
    "get": 2,
    "balancing": 2,
    "quite": 2,
    "right": 2,
    "natives": 2,
    "reported": 2,
    "less": 2,
    "than": 2,
    "bases": 2,
    "conquer": 2,
    "base": 2,
    "quire": 2,
    "apart": 2,
    "minor": 2,
    "energy": 2,
    "during": 2,
    "local": 2,
    "couple": 2,
    "features": 2,
    "notable": 2,
    "these": 2,
    "late": 2,
    "fun": 2,
    "other": 2,
    "issues": 2,
    "more": 2,
    "finished": 2,
    "further": 2,
    "making": 2,
    "thing": 2,
    "busy": 2,
    "do": 2,
    "only": 2,
    "who": 2,
    "account": 2,
    "albert": 2,
    "spawner": 2,
    "had": 2,
    "see": 2,
    "objects": 2,
    "ground": 2,
    "destroyed": 2,
    "episode": 2,
    "recently": 2,
    "conference": 2,
    "waited": 2,
    "advanced": 2,
    "server": 2,
    "management": 2,
    "stuff": 2,
    "year": 2,
    "updates": 2,
    "where": 2,
    "hello": 1,
    "everyone": 1,
    "weekly": 1,
    "update": 1,
    "night": 1,
    "triggered": 1,
    "discussions": 1,
    "seems": 1,
    "end": 1,
    "didnt": 1,
    "rather": 1,
    "overpowered": 1,
    "cases": 1,
    "overrun": 1,
    "half": 1,
    "hour": 1,
    "playing": 1,
    "issue": 1,
    "level": 1,
    "too": 1,
    "quickly": 1,
    "arrives": 1,
    "plenty": 1,
    "medium": 1,
    "big": 1,
    "resistant": 1,
    "relatively": 1,
    "smooth": 1,
    "bugs": 1,
    "no": 1,
    "deal": 1,
    "brakers": 1,
    "recharging": 1,
    "weekend": 1,
    "wine": 1,
    "festival": 1,
    "working": 1,
    "unlike": 1,
    "previous": 1,
    "releases": 1,
    "contain": 1,
    "most": 1,
    "addition": 1,
    "following": 1,
    "robots": 1,
    "aka": 1,
    "destroyers": 1,
    "expensive": 1,
    "allow": 1,
    "even": 1,
    "large": 1,
    "play": 1,
    "their": 1,
    "acceleration": 1,
    "based": 1,
    "behavior": 1,
    "spent": 1,
    "mostly": 1,
    "bugfixing": 1,
    "community": 1,
    "playtesting": 1,
    "expected": 1,
    "released": 1,
    "next": 1,
    "mentioned": 1,
    "before": 1,
    "afterwards": 1,
    "focus": 1,
    "our": 1,
    "trailer": 1,
    "preparing": 1,
    "steam": 1,
    "greenlight": 1,
    "campaign": 1,
    "kept": 1,
    "originally": 1,
    "spammed": 1,
    "degree": 1,
    "any": 1,
    "ressurection": 1,
    "seemed": 1,
    "hopeless": 1,
    "however": 1,
    "many": 1,
    "tries": 1,
    "gb": 1,
    "sql": 1,
    "dump": 1,
    "file": 1,
    "blue": 1,
    "cube": 1,
    "managed": 1,
    "prune": 1,
    "database": 1,
    "resurrect": 1,
    "its": 1,
    "original": 1,
    "location": 1,
    "restricted": 1,
    "access": 1,
    "confirmed": 1,
    "manually": 1,
    "if": 1,
    "interested": 1,
    "contributing": 1,
    "welcomed": 1,
    "then": 1,
    "request": 1,
    "page": 1,
    "need": 1,
    "avoid": 1,
    "automated": 1,
    "spamming": 1,
    "not": 1,
    "resurrected": 1,
    "thanx": 1,
    "kovarex": 1,
    "contains": 1,
    "date": 1,
    "information": 1,
    "scripting": 1,
    "interface": 1,
    "productive": 1,
    "redo": 1,
    "times": 1,
    "noise": 1,
    "final": 1,
    "resulting": 1,
    "imho": 1,
    "worth": 1,
    "below": 1,
    "breathing": 1,
    "together": 1,
    "gif": 1,
    "capturing": 1,
    "process": 1,
    "model": 1,
    "worked": 1,
    "putting": 1,
    "off": 1,
    "things": 1,
    "like": 1,
    "slowdown": 1,
    "particles": 1,
    "underground": 1,
    "indication": 1,
    "belts": 1,
    "pipes": 1,
    "finally": 1,
    "remnants": 1,
    "especially": 1,
    "useful": 1,
    "your": 1,
    "attacked": 1,
    "fact": 1,
    "technically": 1,
    "funny": 1,
    "still": 1,
    "qualifies": 1,
    "looked": 1,
    "prague": 1,
    "super": 1,
    "excited": 1,
    "three": 1,
    "went": 1,
    "really": 1,
    "enthusiastic": 1,
    "talk": 1,
    "industry": 1,
    "maybe": 1,
    "propagate": 1,
    "something": 1,
    "took": 1,
    "place": 1,
    "startup": 1,
    "hub": 1,
    "arrived": 1,
    "saw": 1,
    "start": 1,
    "soon": 1,
    "sat": 1,
    "down": 1,
    "little": 1,
    "bit": 1,
    "weird": 1,
    "nothing": 1,
    "happening": 1,
    "guy": 1,
    "appeared": 1,
    "said": 1,
    "coming": 1,
    "explaining": 1,
    "does": 1,
    "very": 1,
    "time": 1,
    "part": 1,
    "never": 1,
    "turned": 1,
    "out": 1,
    "actually": 1,
    "ago": 1,
    "same": 1,
    "day": 1,
    "one": 1,
    "reception": 1,
    "good": 1,
    "laugh": 1,
    "back": 1,
    "reality": 1,
    "created": 1,
    "category": 1,
    "try": 1,
    "regularly": 1,
    "create": 1,
    "every": 1,
    "facts": 1,
    "comments": 1
  }
}